github_downloader/__init__.py
github_downloader/cli.py
github_downloader/downloader.py
github_content_downloader-0.1.3.dist-info/METADATA
github_content_downloader-0.1.3.dist-info/WHEEL
github_content_downloader-0.1.3.dist-info/entry_points.txt
github_content_downloader-0.1.3.dist-info/top_level.txt
github_content_downloader-0.1.3.dist-info/RECORD
