Metadata-Version: 2.1
Name: github-content-downloader
Version: 0.1.3
Summary: Download any file or folder from GitHub repositories without cloning
Home-page: https://github.com/soykot2910/github-content-downloader
Author: Md.Soykot
Author-email: md.soykot2910@gmail.com
Requires-Python: >=3.6
Requires-Dist: requests>=2.25.0
